insecure_package/__init__.py
insecure_package/insecure_package.py
insecure_package-0.1.0.dist-info/DESCRIPTION.rst
insecure_package-0.1.0.dist-info/METADATA
insecure_package-0.1.0.dist-info/RECORD
insecure_package-0.1.0.dist-info/WHEEL
insecure_package-0.1.0.dist-info/metadata.json
insecure_package-0.1.0.dist-info/top_level.txt
