Metadata-Version: 1.1
Name: insecure-package
Version: 0.1.0
Summary: Insecure Package, don't use it
Home-page: https://github.com/pyupio/insecure_package
Author: pyup.io
Author-email: support@pyup.io
License: MIT license
Keywords: insecure_package
Platform: UNKNOWN
Classifier: Development Status :: 2 - Pre-Alpha
Classifier: Intended Audience :: Developers
Classifier: License :: OSI Approved :: MIT License
Classifier: Natural Language :: English
Classifier: Programming Language :: Python :: 2
Classifier: Programming Language :: Python :: 2.6
Classifier: Programming Language :: Python :: 2.7
Classifier: Programming Language :: Python :: 3
Classifier: Programming Language :: Python :: 3.3
Classifier: Programming Language :: Python :: 3.4
Classifier: Programming Language :: Python :: 3.5
